[
  {
    "inputs": [
      {
        "internalType": "address",
        "name": "addrRegistry",
        "type": "address"
      }
    ],
    "stateMutability": "nonpayable",
    "type": "constructor"
  },
  {
    "anonymous": false,
    "inputs": [
      {
        "indexed": true,
        "internalType": "bytes32",
        "name": "topicID",
        "type": "bytes32"
      },
      {
        "indexed": true,
        "internalType": "address",
        "name": "addr",
        "type": "address"
      },
      {
        "indexed": true,
        "internalType": "bytes32",
        "name": "execProposalID",
        "type": "bytes32"
      },
      {
        "indexed": false,
        "internalType": "bytes32",
        "name": "nowProposalID",
        "type": "bytes32"
      },
      {
        "indexed": false,
        "internalType": "bytes",
        "name": "message",
        "type": "bytes"
      }
    ],
    "name": "EMessage",
    "type": "event"
  },
  {
    "inputs": [],
    "name": "addrRegistry",
    "outputs": [
      {
        "internalType": "contract IAddressRegistry",
        "name": "",
        "type": "address"
      }
    ],
    "stateMutability": "view",
    "type": "function"
  },
  {
    "inputs": [
      {
        "internalType": "bytes32",
        "name": "execProposalID",
        "type": "bytes32"
      },
      {
        "internalType": "bytes",
        "name": "message",
        "type": "bytes"
      }
    ],
    "name": "execMessage",
    "outputs": [],
    "stateMutability": "nonpayable",
    "type": "function"
  },
  {
    "inputs": [
      {
        "internalType": "address",
        "name": "addrReg",
        "type": "address"
      }
    ],
    "name": "init",
    "outputs": [],
    "stateMutability": "nonpayable",
    "type": "function"
  }
]
